README.rst
setup.py
hesiod53_jumpcloud.egg-info/PKG-INFO
hesiod53_jumpcloud.egg-info/SOURCES.txt
hesiod53_jumpcloud.egg-info/dependency_links.txt
hesiod53_jumpcloud.egg-info/entry_points.txt
hesiod53_jumpcloud.egg-info/requires.txt
hesiod53_jumpcloud.egg-info/top_level.txt
jumpcloud/__init__.py
jumpcloud/jumpcloud.py